musket_text/__init__.py
musket_text/preprocessors.py
musket_text/text_datasets.py
musket_text/bert/__init__.py
musket_text/bert/bert_encoder.py
musket_text/bert/embedding.py
musket_text/bert/extract_features.py
musket_text/bert/funcs.py
musket_text/bert/input_constructor.py
musket_text/bert/layers.py
musket_text/bert/load.py
musket_text/bert/model.py
musket_text/bert/modeling.py
musket_text/bert/tokenization.py
musket_text/bert/train.py
musket_text/bert/worker.py
musket_text/bert/data/__init__.py
musket_text/bert/data/dataset.py
musket_text/bert/data/lm_dataset.py
musket_text/bert/data/vocab.py
musket_text-0.443.dist-info/LICENSE
musket_text-0.443.dist-info/METADATA
musket_text-0.443.dist-info/WHEEL
musket_text-0.443.dist-info/dependency_links.txt
musket_text-0.443.dist-info/top_level.txt
musket_text-0.443.dist-info/RECORD
