Metadata-Version: 2.1
Name: musket-text
Version: 0.443
Summary: Text support for Musket ML
Home-page: https://github.com/musket-ml/musket_text
Author: Petrochenko Pavel
Author-email: petrochenko.pavel.a@gmail.com
License: MIT
Platform: UNKNOWN
Requires-Dist: musket-core
Requires-Dist: seqeval
